<?xml version="1.0" encoding="UTF-8" standalone="yes"?>
<symbolBean>
    <value>10MHz</value>
    <rotation>0</rotation>
    <xLoc>0</xLoc>
    <yLoc>0</yLoc>
    <index>836</index>
    <color>
        <red>0</red>
        <green>0</green>
        <blue>0</blue>
    </color>
    <layer>0</layer>
    <name>elektor-Quarz</name>
    <category>Piezoelectric</category>
    <width>70</width>
    <height>64</height>
    <lines>
        <xLoc>0</xLoc>
        <yLoc>0</yLoc>
        <index>0</index>
        <color>
            <red>0</red>
            <green>0</green>
            <blue>0</blue>
        </color>
        <layer>0</layer>
        <start>
            <x>40</x>
            <y>41</y>
        </start>
        <end>
            <x>56</x>
            <y>41</y>
        </end>
        <startType>STRAIGHT</startType>
        <endType>STRAIGHT</endType>
        <thickness>6.0</thickness>
        <dashPhase>0.0</dashPhase>
        <endCap>2</endCap>
        <lineJoin>0</lineJoin>
        <miterLimit>10.0</miterLimit>
    </lines>
    <lines>
        <xLoc>0</xLoc>
        <yLoc>0</yLoc>
        <index>0</index>
        <color>
            <red>0</red>
            <green>0</green>
            <blue>0</blue>
        </color>
        <layer>0</layer>
        <start>
            <x>48</x>
            <y>64</y>
        </start>
        <end>
            <x>48</x>
            <y>45</y>
        </end>
        <startType>STRAIGHT</startType>
        <endType>STRAIGHT</endType>
        <thickness>2.0</thickness>
        <dashPhase>0.0</dashPhase>
        <endCap>2</endCap>
        <lineJoin>0</lineJoin>
        <miterLimit>10.0</miterLimit>
    </lines>
    <lines>
        <xLoc>0</xLoc>
        <yLoc>0</yLoc>
        <index>0</index>
        <color>
            <red>0</red>
            <green>0</green>
            <blue>0</blue>
        </color>
        <layer>0</layer>
        <start>
            <x>40</x>
            <y>23</y>
        </start>
        <end>
            <x>56</x>
            <y>23</y>
        </end>
        <startType>STRAIGHT</startType>
        <endType>STRAIGHT</endType>
        <thickness>6.0</thickness>
        <dashPhase>0.0</dashPhase>
        <endCap>2</endCap>
        <lineJoin>0</lineJoin>
        <miterLimit>10.0</miterLimit>
    </lines>
    <lines>
        <xLoc>0</xLoc>
        <yLoc>0</yLoc>
        <index>0</index>
        <color>
            <red>0</red>
            <green>0</green>
            <blue>0</blue>
        </color>
        <layer>0</layer>
        <start>
            <x>48</x>
            <y>19</y>
        </start>
        <end>
            <x>48</x>
            <y>0</y>
        </end>
        <startType>STRAIGHT</startType>
        <endType>STRAIGHT</endType>
        <thickness>2.0</thickness>
        <dashPhase>0.0</dashPhase>
        <endCap>2</endCap>
        <lineJoin>0</lineJoin>
        <miterLimit>10.0</miterLimit>
    </lines>
    <boxes>
        <xLoc>26</xLoc>
        <yLoc>36</yLoc>
        <index>831</index>
        <color>
            <red>0</red>
            <green>0</green>
            <blue>0</blue>
        </color>
        <layer>2</layer>
        <width>15</width>
        <height>-7</height>
        <thickness>2.0</thickness>
        <dashPhase>0.0</dashPhase>
        <endCap>2</endCap>
        <lineJoin>0</lineJoin>
        <miterLimit>10.0</miterLimit>
        <style>OUTLINED</style>
    </boxes>
    <boxes>
        <xLoc>10</xLoc>
        <yLoc>23</yLoc>
        <index>832</index>
        <color>
            <red>0</red>
            <green>0</green>
            <blue>0</blue>
        </color>
        <layer>2</layer>
        <width>-3</width>
        <height>2</height>
        <thickness>2.0</thickness>
        <dashPhase>0.0</dashPhase>
        <endCap>2</endCap>
        <lineJoin>0</lineJoin>
        <miterLimit>10.0</miterLimit>
        <style>OUTLINED</style>
    </boxes>
    <boxes>
        <xLoc>26</xLoc>
        <yLoc>29</yLoc>
        <index>833</index>
        <color>
            <red>0</red>
            <green>0</green>
            <blue>0</blue>
        </color>
        <layer>2</layer>
        <width>44</width>
        <height>6</height>
        <thickness>2.0</thickness>
        <dashPhase>0.0</dashPhase>
        <endCap>2</endCap>
        <lineJoin>0</lineJoin>
        <miterLimit>10.0</miterLimit>
        <style>OUTLINED</style>
    </boxes>
    <textparts>
        <xLoc>17</xLoc>
        <yLoc>1</yLoc>
        <index>0</index>
        <color>
            <red>0</red>
            <green>0</green>
            <blue>0</blue>
        </color>
        <layer>0</layer>
        <width>0</width>
        <height>0</height>
        <rotation>0</rotation>
        <text>X#</text>
        <font>Arial</font>
        <fontsize>12</fontsize>
        <type>NAME</type>
    </textparts>
    <textparts>
        <xLoc>0</xLoc>
        <yLoc>49</yLoc>
        <index>0</index>
        <color>
            <red>0</red>
            <green>0</green>
            <blue>0</blue>
        </color>
        <layer>0</layer>
        <width>0</width>
        <height>0</height>
        <rotation>0</rotation>
        <text>10MHz</text>
        <font>Arial</font>
        <fontsize>12</fontsize>
        <type>VALUE</type>
    </textparts>
    <mirrorVertical>false</mirrorVertical>
    <mirrorHorizontal>false</mirrorHorizontal>
    <macroMode>true</macroMode>
    <connections>
        <pin>
            <x>48</x>
            <y>0</y>
            <num>1</num>
            <name>1</name>
            <orientation>BOTTOM_RIGHT</orientation>
        </pin>
        <pin>
            <x>48</x>
            <y>64</y>
            <num>2</num>
            <name>2</name>
            <orientation>BOTTOM_RIGHT</orientation>
        </pin>
    </connections>
    <customModel>false</customModel>
    <filename>elektor-Quarz.xml</filename>
</symbolBean>
